dxtorchutils/__init__.py
dxtorchutils/ImageClassification/__init__.py
dxtorchutils/ImageClassification/dataset.py
dxtorchutils/ImageClassification/html_gene.py
dxtorchutils/ImageClassification/validate.py
dxtorchutils/ImageClassification/models/AlexNet.py
dxtorchutils/ImageClassification/models/GoogLeNet.py
dxtorchutils/ImageClassification/models/LeNet5.py
dxtorchutils/ImageClassification/models/ResNet.py
dxtorchutils/ImageClassification/models/VGG.py
dxtorchutils/ImageClassification/models/__init__.py
dxtorchutils/SemanticSegmentation/__init__.py
dxtorchutils/SemanticSegmentation/dataset.py
dxtorchutils/SemanticSegmentation/html_gene.py
dxtorchutils/SemanticSegmentation/validate.py
dxtorchutils/SemanticSegmentation/models/DeeplabV1.py
dxtorchutils/SemanticSegmentation/models/DeeplabV2.py
dxtorchutils/SemanticSegmentation/models/DeeplabV3.py
dxtorchutils/SemanticSegmentation/models/DenseASPP.py
dxtorchutils/SemanticSegmentation/models/FCN.py
dxtorchutils/SemanticSegmentation/models/UNet.py
dxtorchutils/SemanticSegmentation/models/__init__.py
dxtorchutils/utils/__init__.py
dxtorchutils/utils/html_gene.py
dxtorchutils/utils/info_logger.py
dxtorchutils/utils/optimizers.py
dxtorchutils/utils/pretrained_module.py
dxtorchutils/utils/train.py
dxtorchutils/utils/utils.py
torch_utils/__init__.py
torch_utils/models/AlexNet.py
torch_utils/models/DeeplabV1.py
torch_utils/models/DeeplabV2.py
torch_utils/models/DeeplabV3.py
torch_utils/models/DenseASPP.py
torch_utils/models/FCN.py
torch_utils/models/GoogLeNet.py
torch_utils/models/LeNet5.py
torch_utils/models/ResNet.py
torch_utils/models/UNet.py
torch_utils/models/VGG.py
torch_utils/models/__init__.py
torch_utils/utils/Dataset.py
torch_utils/utils/HTMLGene.py
torch_utils/utils/Optimizer.py
torch_utils/utils/Others.py
torch_utils/utils/Train.py
torch_utils/utils/Validate.py
torch_utils/utils/__init__.py
torch_utils/utils/test.py
dxtorchutils-0.0.19.dist-info/LICENSE
dxtorchutils-0.0.19.dist-info/METADATA
dxtorchutils-0.0.19.dist-info/WHEEL
dxtorchutils-0.0.19.dist-info/top_level.txt
dxtorchutils-0.0.19.dist-info/RECORD
