Metadata-Version: 2.1
Name: dxtorchutils
Version: 0.0.19
Summary: Some utils and models in pytorch
Home-page: https://github.com/Ian-Dx/DxTorchUtils
Author: IanDx
Author-email: IanDxSSXX@gmail.com
License: UNKNOWN
Platform: UNKNOWN
Classifier: Programming Language :: Python :: 3
Classifier: License :: OSI Approved :: MIT License
Classifier: Operating System :: OS Independent
Requires-Python: >=3.6
